wonderingpanda510-0.1.13.dist-info/METADATA
wonderingpanda510-0.1.13.dist-info/WHEEL
wonderingpanda510/.DS_Store
wonderingpanda510/__init__.py
wonderingpanda510/_core.abi3.so
wonderingpanda510/_core.pyi
wonderingpanda510/differential/__init__.py
wonderingpanda510/differential/discrete.py
wonderingpanda510/distributions/.DS_Store
wonderingpanda510/distributions/__init__.py
wonderingpanda510/distributions/cvdistributions.py
wonderingpanda510/matrix/.DS_Store
wonderingpanda510/matrix/__init__.py
wonderingpanda510/matrix/elementary.py
wonderingpanda510/model/__init__.py
wonderingpanda510/model/logit.py
wonderingpanda510/model/regression.py
wonderingpanda510/py.typed
wonderingpanda510-0.1.13.dist-info/RECORD
