Metadata-Version: 2.4
Name: wonderingpanda510
Version: 0.1.13
Requires-Dist: matplotlib>=3.10.6
Requires-Dist: maturin>=1.9.3
Requires-Dist: numpy>=2.3.3
Requires-Dist: polars>=1.34.0
Requires-Dist: scipy>=1.16.2
Requires-Dist: torch>=2.8.0
Requires-Dist: twine>=6.1.0
Summary: Add your description here
Author-email: wonderingpanda510gh <wonderingpanda510@gmail.com>
Requires-Python: >=3.12
